sdfr/SDF.py
sdfr/__init__.py
sdfr/_commit_info.py
sdfr/_loadlib.py
sdfr/libsdfc_shared.so
sdfr/sdf_helper.py
sdfr-1.4.11.dist-info/METADATA
sdfr-1.4.11.dist-info/WHEEL
sdfr-1.4.11.dist-info/RECORD
sdfr-1.4.11.dist-info/licenses/LICENSE
sdfr-1.4.11.dist-info/licenses/LICENSE_README.txt
