Metadata-Version: 2.2
Name: sdfr
Version: 1.4.11
Summary: Python module for processing SDF files
Author-Email: Keith Bennett <k.bennett@warwick.ac.uk>
Requires-Dist: numpy
